[{"name":"00/09-32-064-19W5/0","type":"horizontal"},{"name":"00/06-24-065-20W5/0","type":"horizontal"},{"name":"00/04-24-065-20W5/0","type":"horizontal"},{"name":"03/01-24-065-20W5/0","type":"horizontal"},{"name":"02/16-14-065-20W5/0","type":"horizontal"},{"name":"00/13-17-065-19W5/0","type":"horizontal"},{"name":"00/15-18-065-19W5/0","type":"horizontal"},{"name":"00/01-33-064-19W5/0","type":"horizontal"},{"name":"02/02-33-064-19W5/0","type":"horizontal"},{"name":"00/04-33-064-19W5/0","type":"horizontal"},{"name":"00/04-05-065-20W5/0","type":"horizontal"},{"name":"00/05-05-065-20W5/0","type":"horizontal"},{"name":"02/12-05-065-20W5/0","type":"horizontal"},{"name":"00/11-05-065-20W5/0","type":"horizontal"},{"name":"00/09-29-064-19W5/0","type":"horizontal"},{"name":"00/04-13-065-20W5/0","type":"horizontal"},{"name":"00/08-29-064-19W5/0","type":"horizontal"},{"name":"00/01-29-064-19W5/0","type":"horizontal"},{"name":"00/06-01-065-20W5/0","type":"horizontal"},{"name":"00/04-01-065-20W5/0","type":"horizontal"},{"name":"00/04-12-065-20W5/0","type":"horizontal"},{"name":"00/12-36-064-20W5/0","type":"horizontal"},{"name":"00/05-12-065-20W5/0","type":"horizontal"},{"name":"00/03-28-064-20W5/0","type":"horizontal"},{"name":"00/04-29-064-19W5/0","type":"horizontal"},{"name":"03/01-07-065-19W5/0","type":"horizontal"},{"name":"02/03-14-064-19W5/0","type":"horizontal"},{"name":"00/13-17-063-19W5/0","type":"horizontal"},{"name":"03/06-20-063-19W5/0","type":"horizontal"},{"name":"00/11-04-063-20W5/0","type":"horizontal"},{"name":"02/14-04-063-20W5/0","type":"horizontal"},{"name":"00/14-11-064-19W5/0","type":"horizontal"},{"name":"00/11-11-064-19W5/0","type":"horizontal"},{"name":"00/13-32-063-19W5/0","type":"horizontal"},{"name":"00/07-06-064-19W5/0","type":"horizontal"},{"name":"00/03-06-064-19W5/0","type":"horizontal"},{"name":"03/04-06-064-19W5/0","type":"horizontal"},{"name":"04/08-20-063-19W5/0","type":"horizontal"},{"name":"02/12-33-063-19W5/0","type":"horizontal"},{"name":"02/06-28-063-19W5/0","type":"horizontal"},{"name":"00/09-29-064-19W5/0","type":"horizontal"},{"name":"00/08-29-064-19W5/0","type":"horizontal"},{"name":"02/04-13-064-20W5/0","type":"horizontal"},{"name":"02/14-22-064-20W5/0","type":"horizontal"},{"name":"00/16-21-064-20W5/0","type":"horizontal"},{"name":"02/08-03-064-20W5/0","type":"horizontal"},{"name":"00/10-03-064-20W5/0","type":"horizontal"},{"name":"02/15-21-064-20W5/0","type":"horizontal"},{"name":"02/13-21-064-20W5/0","type":"horizontal"},{"name":"00/01-29-064-19W5/0","type":"horizontal"},{"name":"00/06-01-065-20W5/0","type":"horizontal"},{"name":"02/01-18-064-19W5/0","type":"horizontal"},{"name":"00/04-01-065-20W5/0","type":"horizontal"},{"name":"00/04-12-065-20W5/0","type":"horizontal"},{"name":"00/12-36-064-20W5/0","type":"horizontal"},{"name":"00/05-12-065-20W5/0","type":"horizontal"},{"name":"00/13-21-064-20W5/0","type":"horizontal"},{"name":"00/05-21-064-20W5/0","type":"horizontal"},{"name":"00/16-17-064-20W5/0","type":"horizontal"},{"name":"00/14-17-064-20W5/0","type":"horizontal"},{"name":"00/16-23-064-20W5/0","type":"horizontal"},{"name":"00/05-06-064-19W5/0","type":"horizontal"},{"name":"02/02-30-064-19W5/0","type":"horizontal"},{"name":"00/14-23-064-20W5/0","type":"horizontal"},{"name":"00/13-23-064-20W5/0","type":"horizontal"},{"name":"00/16-22-064-20W5/0","type":"horizontal"},{"name":"02/01-29-063-19W5/0","type":"horizontal"},{"name":"00/03-28-064-20W5/0","type":"horizontal"},{"name":"02/07-34-063-20W5/0","type":"horizontal"},{"name":"02/16-14-063-20W5/0","type":"horizontal"},{"name":"00/13-26-063-20W5/0","type":"horizontal"},{"name":"00/06-09-063-20W5/0","type":"horizontal"},{"name":"02/02-23-063-20W5/0","type":"horizontal"},{"name":"00/07-23-063-20W5/0","type":"horizontal"},{"name":"02/10-23-063-20W5/0","type":"horizontal"},{"name":"03/08-34-063-20W5/0","type":"horizontal"},{"name":"02/12-09-064-20W5/0","type":"horizontal"},{"name":"02/13-09-064-20W5/0","type":"horizontal"},{"name":"04/16-34-063-20W5/0","type":"horizontal"},{"name":"00/04-15-064-20W5/0","type":"horizontal"},{"name":"00/11-15-064-20W5/0","type":"horizontal"},{"name":"03/16-33-063-20W5/0","type":"horizontal"},{"name":"03/13-34-063-20W5/0","type":"horizontal"},{"name":"04/13-34-063-20W5/0","type":"horizontal"},{"name":"02/01-22-063-20W5/0","type":"horizontal"},{"name":"00/14-14-063-20W5/0","type":"horizontal"},{"name":"00/15-14-063-20W5/0","type":"horizontal"},{"name":"00/01-01-063-20W5/0","type":"horizontal"},{"name":"00/13-36-062-20W5/0","type":"horizontal"},{"name":"00/10-36-062-20W5/0","type":"horizontal"},{"name":"04/06-19-063-19W5/0","type":"horizontal"},{"name":"02/07-19-063-19W5/0","type":"horizontal"},{"name":"W0/12-20-063-19W5/0","type":"horizontal"},{"name":"W0/13-20-063-19W5/0","type":"horizontal"},{"name":"W2/13-20-063-19W5/0","type":"horizontal"},{"name":"00/05-13-063-20W5/0","type":"horizontal"},{"name":"00/12-13-063-20W5/0","type":"horizontal"},{"name":"02/11-28-063-20W5/0","type":"horizontal"},{"name":"02/06-28-063-20W5/0","type":"horizontal"},{"name":"00/09-02-063-20W5/0","type":"horizontal"},{"name":"00/05-12-063-20W5/0","type":"horizontal"},{"name":"00/14-12-063-20W5/0","type":"horizontal"},{"name":"00/09-25-063-20W5/0","type":"horizontal"},{"name":"03/01-25-063-20W5/0","type":"horizontal"},{"name":"00/02-25-063-20W5/0","type":"horizontal"},{"name":"03/13-22-063-20W5/0","type":"horizontal"},{"name":"02/04-16-063-20W5/0","type":"horizontal"},{"name":"00/11-22-063-20W5/0","type":"horizontal"},{"name":"00/04-16-063-20W5/0","type":"horizontal"},{"name":"00/09-21-063-20W5/0","type":"horizontal"},{"name":"02/07-20-063-19W5/0","type":"horizontal"},{"name":"00/07-20-063-19W5/0","type":"horizontal"},{"name":"02/06-20-063-19W5/0","type":"horizontal"},{"name":"00/08-19-063-19W5/0","type":"horizontal"},{"name":"03/05-20-063-19W5/0","type":"horizontal"},{"name":"02/08-20-063-19W5/0","type":"horizontal"},{"name":"00/08-20-063-19W5/0","type":"horizontal"},{"name":"02/01-25-063-20W5/0","type":"horizontal"},{"name":"00/06-06-064-19W5/0","type":"horizontal"},{"name":"02/09-12-063-20W5/0","type":"horizontal"},{"name":"04/10-12-063-20W5/0","type":"horizontal"},{"name":"03/10-12-063-20W5/0","type":"horizontal"},{"name":"02/12-12-063-20W5/0","type":"horizontal"},{"name":"05/11-12-063-20W5/0","type":"horizontal"},{"name":"04/11-12-063-20W5/0","type":"horizontal"},{"name":"00/03-20-063-19W5/0","type":"horizontal"},{"name":"02/05-11-063-20W5/0","type":"horizontal"},{"name":"05/07-11-063-20W5/0","type":"horizontal"},{"name":"02/06-11-063-20W5/0","type":"horizontal"},{"name":"03/05-11-063-20W5/0","type":"horizontal"},{"name":"04/07-11-063-20W5/0","type":"horizontal"},{"name":"03/07-11-063-20W5/0","type":"horizontal"},{"name":"00/08-36-063-20W5/0","type":"horizontal"},{"name":"00/01-36-063-20W5/0","type":"horizontal"},{"name":"00/11-34-063-20W5/0","type":"horizontal"},{"name":"02/12-34-063-20W5/0","type":"horizontal"},{"name":"W0/12-34-063-20W5/0","type":"horizontal"},{"name":"03/12-34-063-20W5/0","type":"horizontal"},{"name":"00/09-33-063-20W5/0","type":"horizontal"},{"name":"00/10-33-063-20W5/0","type":"horizontal"},{"name":"02/07-16-063-20W5/0","type":"horizontal"},{"name":"02/05-16-063-20W5/0","type":"horizontal"},{"name":"00/08-16-063-20W5/0","type":"horizontal"},{"name":"00/07-17-063-19W5/0","type":"horizontal"},{"name":"00/13-21-063-19W5/0","type":"horizontal"},{"name":"00/10-17-063-19W5/0","type":"horizontal"},{"name":"00/09-10-064-19W5/0","type":"horizontal"},{"name":"00/07-16-063-20W5/0","type":"horizontal"},{"name":"02/06-16-063-20W5/0","type":"horizontal"},{"name":"00/06-16-063-20W5/0","type":"horizontal"},{"name":"03/06-16-063-20W5/0","type":"horizontal"},{"name":"W0/05-19-063-19W5/0","type":"horizontal"},{"name":"00/08-24-063-20W5/0","type":"horizontal"},{"name":"00/07-24-063-20W5/0","type":"horizontal"},{"name":"00/06-24-063-20W5/0","type":"horizontal"},{"name":"02/07-11-063-20W5/0","type":"horizontal"},{"name":"00/10-11-063-20W5/0","type":"horizontal"},{"name":"00/06-11-063-20W5/0","type":"horizontal"},{"name":"00/05-11-063-20W5/0","type":"horizontal"},{"name":"00/04-29-064-19W5/0","type":"horizontal"},{"name":"02/02-35-063-20W5/0","type":"horizontal"},{"name":"02/03-19-063-19W5/0","type":"horizontal"},{"name":"00/08-06-063-19W5/0","type":"horizontal"},{"name":"00/07-06-063-19W5/0","type":"horizontal"},{"name":"00/02-01-063-20W5/0","type":"horizontal"},{"name":"00/15-22-063-20W5/0","type":"horizontal"},{"name":"00/11-06-063-19W5/0","type":"horizontal"},{"name":"00/04-25-064-20W5/0","type":"horizontal"},{"name":"00/04-09-063-20W5/0","type":"horizontal"},{"name":"02/04-11-063-20W5/0","type":"horizontal"},{"name":"00/05-20-063-19W5/0","type":"horizontal"},{"name":"00/02-11-064-20W5/0","type":"horizontal"},{"name":"00/04-06-064-19W5/0","type":"horizontal"},{"name":"00/14-06-063-19W5/0","type":"horizontal"},{"name":"00/13-07-064-19W5/0","type":"horizontal"},{"name":"00/16-33-063-20W5/0","type":"horizontal"},{"name":"02/04-02-063-20W5/0","type":"horizontal"},{"name":"00/15-27-063-20W5/0","type":"horizontal"},{"name":"00/15-09-063-20W5/0","type":"horizontal"},{"name":"00/04-15-063-20W5/0","type":"horizontal"},{"name":"02/13-10-063-19W5/0","type":"horizontal"},{"name":"00/04-11-063-20W5/0","type":"horizontal"},{"name":"03/14-27-063-20W5/0","type":"horizontal"},{"name":"02/14-27-063-20W5/0","type":"horizontal"},{"name":"00/04-21-063-20W5/0","type":"horizontal"},{"name":"02/13-14-063-20W5/0","type":"horizontal"},{"name":"00/13-14-063-20W5/0","type":"horizontal"},{"name":"00/07-27-063-19W5/0","type":"horizontal"},{"name":"00/09-28-063-19W5/0","type":"horizontal"},{"name":"00/02-35-063-20W5/0","type":"horizontal"},{"name":"00/10-01-064-20W5/0","type":"horizontal"},{"name":"102/06-04-065-20W5/00","type":"vertical"},{"name":"100/06-04-065-20W5/00","type":"vertical"},{"name":"100/10-02-065-20W5/02","type":"vertical"},{"name":"100/10-02-065-20W5/00","type":"vertical"},{"name":"100/03-01-065-20W5/00","type":"vertical"},{"name":"100/07-04-065-19W5/00","type":"vertical"},{"name":"100/02-04-065-19W5/00","type":"vertical"},{"name":"100/06-36-064-20W5/00","type":"vertical"},{"name":"100/07-34-064-20W5/00","type":"vertical"},{"name":"100/12-34-064-19W5/00","type":"vertical"},{"name":"100/04-34-064-19W5/00","type":"vertical"},{"name":"100/02-33-064-19W5/00","type":"vertical"},{"name":"100/07-31-064-19W5/00","type":"vertical"},{"name":"100/15-28-064-19W5/00","type":"vertical"},{"name":"100/02-28-064-20W5/00","type":"vertical"},{"name":"100/10-26-064-20W5/00","type":"vertical"},{"name":"100/10-24-064-20W5/02","type":"vertical"},{"name":"100/10-24-064-20W5/00","type":"vertical"},{"name":"102/07-16-064-20W5/00","type":"vertical"},{"name":"100/07-16-064-20W5/00","type":"vertical"},{"name":"100/10-14-064-20W5/00","type":"vertical"},{"name":"102/01-12-064-20W5/00","type":"vertical"},{"name":"100/01-12-064-20W5/00","type":"vertical"},{"name":"100/12-04-064-20W5/02","type":"vertical"},{"name":"100/12-04-064-20W5/00","type":"vertical"},{"name":"100/08-03-064-20W5/02","type":"vertical"},{"name":"100/08-03-064-20W5/00","type":"vertical"},{"name":"100/08-02-064-20W5/00","type":"vertical"},{"name":"100/06-01-064-20W5/02","type":"vertical"},{"name":"100/06-01-064-20W5/00","type":"vertical"},{"name":"100/10-28-064-19W5/02","type":"vertical"},{"name":"100/10-28-064-19W5/00","type":"vertical"},{"name":"100/02-28-064-19W5/00","type":"vertical"},{"name":"100/12-27-064-19W5/00","type":"vertical"},{"name":"100/04-27-064-19W5/00","type":"vertical"},{"name":"100/12-22-064-19W5/00","type":"vertical"},{"name":"100/04-22-064-19W5/00","type":"vertical"},{"name":"100/12-21-064-19W5/00","type":"vertical"},{"name":"100/04-21-064-19W5/00","type":"vertical"},{"name":"100/02-21-064-19W5/00","type":"vertical"},{"name":"100/08-20-064-19W5/00","type":"vertical"},{"name":"100/06-20-064-19W5/00","type":"vertical"},{"name":"102/02-20-064-19W5/00","type":"vertical"},{"name":"100/02-20-064-19W5/00","type":"vertical"},{"name":"100/12-19-064-19W5/00","type":"vertical"},{"name":"102/10-18-064-19W5/00","type":"vertical"},{"name":"100/10-18-064-19W5/00","type":"vertical"},{"name":"100/09-18-064-19W5/00","type":"vertical"},{"name":"100/01-18-064-19W5/00","type":"vertical"},{"name":"100/12-17-064-19W5/00","type":"vertical"},{"name":"100/10-17-064-19W5/02","type":"vertical"},{"name":"100/10-17-064-19W5/00","type":"vertical"},{"name":"100/06-17-064-19W5/00","type":"vertical"},{"name":"100/04-17-064-19W5/00","type":"vertical"},{"name":"102/02-17-064-19W5/00","type":"vertical"},{"name":"100/02-17-064-19W5/00","type":"vertical"},{"name":"100/15-16-064-19W5/00","type":"vertical"},{"name":"100/12-16-064-19W5/00","type":"vertical"},{"name":"100/10-16-064-19W5/00","type":"vertical"},{"name":"100/04-16-064-19W5/00","type":"vertical"},{"name":"100/02-16-064-19W5/00","type":"vertical"},{"name":"100/12-15-064-19W5/00","type":"vertical"},{"name":"100/04-15-064-19W5/00","type":"vertical"},{"name":"100/12-10-064-19W5/00","type":"vertical"},{"name":"100/04-10-064-19W5/02","type":"vertical"},{"name":"100/04-10-064-19W5/00","type":"vertical"},{"name":"100/12-09-064-19W5/00","type":"vertical"},{"name":"100/10-09-064-19W5/02","type":"vertical"},{"name":"100/10-09-064-19W5/00","type":"vertical"},{"name":"100/08-09-064-19W5/02","type":"vertical"},{"name":"100/04-09-064-19W5/00","type":"vertical"},{"name":"100/02-09-064-19W5/00","type":"vertical"},{"name":"100/12-08-064-19W5/00","type":"vertical"},{"name":"100/10-08-064-19W5/00","type":"vertical"},{"name":"100/04-08-064-19W5/00","type":"vertical"},{"name":"102/02-08-064-19W5/00","type":"vertical"},{"name":"100/02-08-064-19W5/00","type":"vertical"},{"name":"100/10-07-064-19W5/00","type":"vertical"},{"name":"100/04-07-064-19W5/00","type":"vertical"},{"name":"100/02-07-064-19W5/00","type":"vertical"},{"name":"100/01-07-064-19W5/02","type":"vertical"},{"name":"100/01-07-064-19W5/00","type":"vertical"},{"name":"100/15-06-064-19W5/00","type":"vertical"},{"name":"100/12-05-064-19W5/00","type":"vertical"},{"name":"102/10-05-064-19W5/00","type":"vertical"},{"name":"100/10-05-064-19W5/02","type":"vertical"},{"name":"100/10-05-064-19W5/00","type":"vertical"},{"name":"100/04-05-064-19W5/00","type":"vertical"},{"name":"100/02-05-064-19W5/00","type":"vertical"},{"name":"100/12-04-064-19W5/00","type":"vertical"},{"name":"100/11-04-064-19W5/00","type":"vertical"},{"name":"100/10-04-064-19W5/00","type":"vertical"},{"name":"100/04-04-064-19W5/00","type":"vertical"},{"name":"100/02-04-064-19W5/00","type":"vertical"},{"name":"100/12-03-064-19W5/00","type":"vertical"},{"name":"102/13-36-063-20W5/00","type":"vertical"},{"name":"100/13-36-063-20W5/00","type":"vertical"},{"name":"100/03-36-063-20W5/00","type":"vertical"},{"name":"100/15-35-063-20W5/00","type":"vertical"},{"name":"100/04-34-063-20W5/00","type":"vertical"},{"name":"100/03-34-063-20W5/02","type":"vertical"},{"name":"100/03-34-063-20W5/00","type":"vertical"},{"name":"100/06-33-063-20W5/00","type":"vertical"},{"name":"100/08-28-063-20W5/00","type":"vertical"},{"name":"100/07-28-063-20W5/02","type":"vertical"},{"name":"100/07-28-063-20W5/00","type":"vertical"},{"name":"100/02-28-063-20W5/00","type":"vertical"},{"name":"100/16-27-063-20W5/00","type":"vertical"},{"name":"100/11-27-063-20W5/00","type":"vertical"},{"name":"100/07-26-063-20W5/00","type":"vertical"},{"name":"100/10-25-063-20W5/00","type":"vertical"},{"name":"100/03-25-063-20W5/00","type":"vertical"},{"name":"100/01-25-063-20W5/00","type":"vertical"},{"name":"102/01-24-063-20W5/02","type":"vertical"},{"name":"102/01-24-063-20W5/00","type":"vertical"},{"name":"100/01-24-063-20W5/00","type":"vertical"},{"name":"100/10-23-063-20W5/00","type":"vertical"},{"name":"100/10-22-063-20W5/00","type":"vertical"},{"name":"100/14-21-063-20W5/00","type":"vertical"},{"name":"100/06-21-063-20W5/00","type":"vertical"},{"name":"102/11-16-063-20W5/00","type":"vertical"},{"name":"100/11-16-063-20W5/02","type":"vertical"},{"name":"100/11-16-063-20W5/00","type":"vertical"},{"name":"100/13-15-063-20W5/02","type":"vertical"},{"name":"100/13-15-063-20W5/00","type":"vertical"},{"name":"100/02-15-063-20W5/00","type":"vertical"},{"name":"100/01-15-063-20W5/00","type":"vertical"},{"name":"100/11-14-063-20W5/00","type":"vertical"},{"name":"100/08-14-063-20W5/00","type":"vertical"},{"name":"102/04-14-063-20W5/02","type":"vertical"},{"name":"102/04-14-063-20W5/00","type":"vertical"},{"name":"100/04-14-063-20W5/02","type":"vertical"},{"name":"100/04-14-063-20W5/00","type":"vertical"},{"name":"100/16-13-063-20W5/02","type":"vertical"},{"name":"100/16-13-063-20W5/00","type":"vertical"},{"name":"100/11-13-063-20W5/00","type":"vertical"},{"name":"100/08-13-063-20W5/00","type":"vertical"},{"name":"100/04-13-063-20W5/02","type":"vertical"},{"name":"100/04-13-063-20W5/00","type":"vertical"},{"name":"100/16-12-063-20W5/00","type":"vertical"},{"name":"100/11-12-063-20W5/00","type":"vertical"},{"name":"100/03-12-063-20W5/00","type":"vertical"},{"name":"100/02-12-063-20W5/02","type":"vertical"},{"name":"100/02-12-063-20W5/00","type":"vertical"},{"name":"100/13-11-063-20W5/00","type":"vertical"},{"name":"100/09-11-063-20W5/02","type":"vertical"},{"name":"100/09-11-063-20W5/00","type":"vertical"},{"name":"100/10-10-063-20W5/02","type":"vertical"},{"name":"100/10-10-063-20W5/00","type":"vertical"},{"name":"100/16-09-063-20W5/02","type":"vertical"},{"name":"100/16-09-063-20W5/00","type":"vertical"},{"name":"100/10-03-063-20W5/00","type":"vertical"},{"name":"100/13-02-063-20W5/00","type":"vertical"},{"name":"100/10-01-063-20W5/02","type":"vertical"},{"name":"100/10-01-063-20W5/00","type":"vertical"},{"name":"100/12-34-063-19W5/00","type":"vertical"},{"name":"100/04-34-063-19W5/00","type":"vertical"},{"name":"100/12-33-063-19W5/00","type":"vertical"},{"name":"100/10-33-063-19W5/00","type":"vertical"},{"name":"100/09-33-063-19W5/02","type":"vertical"},{"name":"100/09-33-063-19W5/00","type":"vertical"},{"name":"1F1/07-33-063-19W5/00","type":"vertical"},{"name":"100/07-33-063-19W5/00","type":"vertical"},{"name":"100/05-33-063-19W5/00","type":"vertical"},{"name":"1F1/04-33-063-19W5/00","type":"vertical"},{"name":"100/04-33-063-19W5/00","type":"vertical"},{"name":"100/11-32-063-19W5/00","type":"vertical"},{"name":"100/10-32-063-19W5/00","type":"vertical"},{"name":"100/03-32-063-19W5/02","type":"vertical"},{"name":"100/03-32-063-19W5/00","type":"vertical"},{"name":"100/02-32-063-19W5/00","type":"vertical"},{"name":"100/01-32-063-19W5/00","type":"vertical"},{"name":"100/16-31-063-19W5/02","type":"vertical"},{"name":"100/16-31-063-19W5/00","type":"vertical"},{"name":"100/11-29-063-19W5/00","type":"vertical"},{"name":"100/10-29-063-19W5/00","type":"vertical"},{"name":"100/04-29-063-19W5/02","type":"vertical"},{"name":"100/04-29-063-19W5/00","type":"vertical"},{"name":"100/12-28-063-19W5/02","type":"vertical"},{"name":"100/12-28-063-19W5/00","type":"vertical"},{"name":"102/10-28-063-19W5/02","type":"vertical"},{"name":"102/10-28-063-19W5/00","type":"vertical"},{"name":"100/10-28-063-19W5/00","type":"vertical"},{"name":"100/06-28-063-19W5/02","type":"vertical"},{"name":"100/06-28-063-19W5/00","type":"vertical"},{"name":"100/04-28-063-19W5/00","type":"vertical"},{"name":"100/02-28-063-19W5/00","type":"vertical"},{"name":"100/12-27-063-19W5/02","type":"vertical"},{"name":"100/12-27-063-19W5/00","type":"vertical"},{"name":"100/04-27-063-19W5/02","type":"vertical"},{"name":"100/04-27-063-19W5/00","type":"vertical"},{"name":"102/12-22-063-19W5/02","type":"vertical"},{"name":"102/12-22-063-19W5/00","type":"vertical"},{"name":"100/12-22-063-19W5/00","type":"vertical"},{"name":"102/04-22-063-19W5/00","type":"vertical"},{"name":"100/04-22-063-19W5/00","type":"vertical"},{"name":"100/16-21-063-19W5/00","type":"vertical"},{"name":"1F2/14-21-063-19W5/00","type":"vertical"},{"name":"1F1/14-21-063-19W5/00","type":"vertical"},{"name":"100/14-21-063-19W5/02","type":"vertical"},{"name":"100/14-21-063-19W5/00","type":"vertical"},{"name":"1F1/10-21-063-19W5/00","type":"vertical"},{"name":"100/10-21-063-19W5/02","type":"vertical"},{"name":"100/10-21-063-19W5/00","type":"vertical"},{"name":"100/08-21-063-19W5/02","type":"vertical"},{"name":"100/08-21-063-19W5/00","type":"vertical"},{"name":"100/12-19-063-19W5/00","type":"vertical"},{"name":"100/07-19-063-19W5/00","type":"vertical"},{"name":"100/05-19-063-19W5/00","type":"vertical"},{"name":"100/03-19-063-19W5/00","type":"vertical"},{"name":"100/02-19-063-19W5/00","type":"vertical"},{"name":"100/13-18-063-19W5/00","type":"vertical"},{"name":"100/10-18-063-19W5/02","type":"vertical"},{"name":"100/10-18-063-19W5/00","type":"vertical"},{"name":"100/08-16-063-19W5/02","type":"vertical"},{"name":"100/08-16-063-19W5/00","type":"vertical"},{"name":"102/03-16-063-19W5/00","type":"vertical"},{"name":"100/03-16-063-19W5/00","type":"vertical"},{"name":"100/14-09-063-19W5/02","type":"vertical"},{"name":"100/14-09-063-19W5/00","type":"vertical"},{"name":"100/14-08-063-19W5/02","type":"vertical"},{"name":"100/14-08-063-19W5/00","type":"vertical"},{"name":"100/05-08-063-19W5/02","type":"vertical"},{"name":"100/05-08-063-19W5/00","type":"vertical"},{"name":"100/10-07-063-19W5/02","type":"vertical"},{"name":"100/10-07-063-19W5/00","type":"vertical"},{"name":"100/04-07-063-19W5/02","type":"vertical"},{"name":"100/04-07-063-19W5/00","type":"vertical"},{"name":"100/12-06-063-19W5/02","type":"vertical"},{"name":"100/12-06-063-19W5/00","type":"vertical"},{"name":"100/12-05-063-19W5/00","type":"vertical"}]